X2021NiukeHulianwangKaiguaGonglveFix1/README.md
X2021NiukeHulianwangKaiguaGonglveFix1/__init__.py
X2021NiukeHulianwangKaiguaGonglveFix1/__main__.py
X2021NiukeHulianwangKaiguaGonglveFix1/file.epub
X2021NiukeHulianwangKaiguaGonglveFix1/index.html
X2021NiukeHulianwangKaiguaGonglveFix1/css/__init__.py
X2021NiukeHulianwangKaiguaGonglveFix1/css/annotations.css
X2021NiukeHulianwangKaiguaGonglveFix1/css/main.css
X2021NiukeHulianwangKaiguaGonglveFix1/css/normalize.css
X2021NiukeHulianwangKaiguaGonglveFix1/css/popup.css
X2021NiukeHulianwangKaiguaGonglveFix1/font/__init__.py
X2021NiukeHulianwangKaiguaGonglveFix1/font/fontello.eot
X2021NiukeHulianwangKaiguaGonglveFix1/font/fontello.svg
X2021NiukeHulianwangKaiguaGonglveFix1/font/fontello.ttf
X2021NiukeHulianwangKaiguaGonglveFix1/font/fontello.woff
X2021NiukeHulianwangKaiguaGonglveFix1/img/__init__.py
X2021NiukeHulianwangKaiguaGonglveFix1/img/annotator-glyph-sprite.png
X2021NiukeHulianwangKaiguaGonglveFix1/img/annotator-icon-sprite.png
X2021NiukeHulianwangKaiguaGonglveFix1/img/apple-touch-icon.png
X2021NiukeHulianwangKaiguaGonglveFix1/img/cancelfullscreen.png
X2021NiukeHulianwangKaiguaGonglveFix1/img/close.png
X2021NiukeHulianwangKaiguaGonglveFix1/img/fullscreen.png
X2021NiukeHulianwangKaiguaGonglveFix1/img/loader.gif
X2021NiukeHulianwangKaiguaGonglveFix1/img/menu-icon.png
X2021NiukeHulianwangKaiguaGonglveFix1/img/save.png
X2021NiukeHulianwangKaiguaGonglveFix1/img/saved.png
X2021NiukeHulianwangKaiguaGonglveFix1/img/settings-s.png
X2021NiukeHulianwangKaiguaGonglveFix1/img/settings.png
X2021NiukeHulianwangKaiguaGonglveFix1/img/star.png
X2021NiukeHulianwangKaiguaGonglveFix1/js/__init__.py
X2021NiukeHulianwangKaiguaGonglveFix1/js/epub.js
X2021NiukeHulianwangKaiguaGonglveFix1/js/epub.min.js
X2021NiukeHulianwangKaiguaGonglveFix1/js/epub.min.map
X2021NiukeHulianwangKaiguaGonglveFix1/js/hooks.min.js
X2021NiukeHulianwangKaiguaGonglveFix1/js/hooks.min.map
X2021NiukeHulianwangKaiguaGonglveFix1/js/reader.js
x2021_niuke_hulianwang_kaigua_gonglve_fix1-2025.3.25.0.dist-info/METADATA
x2021_niuke_hulianwang_kaigua_gonglve_fix1-2025.3.25.0.dist-info/WHEEL
x2021_niuke_hulianwang_kaigua_gonglve_fix1-2025.3.25.0.dist-info/entry_points.txt
x2021_niuke_hulianwang_kaigua_gonglve_fix1-2025.3.25.0.dist-info/top_level.txt
x2021_niuke_hulianwang_kaigua_gonglve_fix1-2025.3.25.0.dist-info/RECORD
